[
  {
    "_id": "56f77669940a4faae1617aea",
    "device": "xDrip-BluetoothWixel",
    "date": 1459058278051,
    "dateString": "03/27/2016 06:57:58 a.m.",
    "sgv": 145,
    "direction": "Flat",
    "type": "sgv",
    "filtered": 154688,
    "unfiltered": 154688,
    "rssi": 100,
    "noise": 1,
    "glucose": 145
  },
  {
    "_id": "56f7753d940a4faae1617ae4",
    "device": "xDrip-BluetoothWixel",
    "date": 1459057978070,
    "dateString": "03/27/2016 06:52:58 a.m.",
    "sgv": 147,
    "direction": "Flat",
    "type": "sgv",
    "filtered": 156704,
    "unfiltered": 156704,
    "rssi": 100,
    "noise": 1,
    "glucose": 147
  },
  {
    "_id": "56f77411940a4faae1617add",
    "device": "xDrip-BluetoothWixel",
    "date": 1459057678056,
    "dateString": "03/27/2016 06:47:58 a.m.",
    "sgv": 151,
    "direction": "Flat",
    "type": "sgv",
    "filtered": 159808,
    "unfiltered": 159808,
    "rssi": 100,
    "noise": 1,
    "glucose": 151
  },
  {
    "_id": "56f772e4940a4faae1617ad7",
    "device": "xDrip-BluetoothWixel",
    "date": 1459057377885,
    "dateString": "03/27/2016 06:42:57 a.m.",
    "sgv": 152,
    "direction": "Flat",
    "type": "sgv",
    "filtered": 160608,
    "unfiltered": 160608,
    "rssi": 100,
    "noise": 1,
    "glucose": 152
  },
  {
    "_id": "56f771b8940a4faae1617ad1",
    "device": "xDrip-BluetoothWixel",
    "date": 1459057077875,
    "dateString": "03/27/2016 06:37:57 a.m.",
    "sgv": 152,
    "direction": "Flat",
    "type": "sgv",
    "filtered": 160768,
    "unfiltered": 160768,
    "rssi": 100,
    "noise": 1,
    "glucose": 152
  },
  {
    "_id": "56f7708d940a4faae1617acb",
    "device": "xDrip-BluetoothWixel",
    "date": 1459056778061,
    "dateString": "03/27/2016 06:32:58 a.m.",
    "sgv": 153,
    "direction": "Flat",
    "type": "sgv",
    "filtered": 161184,
    "unfiltered": 161184,
    "rssi": 100,
    "noise": 1,
    "glucose": 153
  },
  {
    "_id": "56f76f60940a4faae1617ac5",
    "device": "xDrip-BluetoothWixel",
    "date": 1459056478113,
    "dateString": "03/27/2016 06:27:58 a.m.",
    "sgv": 152,
    "direction": "Flat",
    "type": "sgv",
    "filtered": 160896,
    "unfiltered": 160896,
    "rssi": 100,
    "noise": 1,
    "glucose": 152
  },
  {
    "_id": "56f76e35940a4faae1617abe",
    "device": "xDrip-BluetoothWixel",
    "date": 1459056178076,
    "dateString": "03/27/2016 06:22:58 a.m.",
    "sgv": 151,
    "direction": "Flat",
    "type": "sgv",
    "filtered": 159680,
    "unfiltered": 159680,
    "rssi": 100,
    "noise": 1,
    "glucose": 151
  },
  {
    "_id": "56f76d0a940a4faae1617ab7",
    "device": "xDrip-BluetoothWixel",
    "date": 1459055878092,
    "dateString": "03/27/2016 06:17:58 a.m.",
    "sgv": 150,
    "direction": "Flat",
    "type": "sgv",
    "filtered": 159200,
    "unfiltered": 159200,
    "rssi": 100,
    "noise": 1,
    "glucose": 150
  },
  {
    "_id": "56f76bdd940a4faae1617aaf",
    "device": "xDrip-BluetoothWixel",
    "date": 1459055577887,
    "dateString": "03/27/2016 06:12:57 a.m.",
    "sgv": 152,
    "direction": "Flat",
    "type": "sgv",
    "filtered": 160288,
    "unfiltered": 160288,
    "rssi": 100,
    "noise": 1,
    "glucose": 152
  }
]
