[
  {
    "_id": "56f36951940a4faae1615c73",
    "device": "xDrip-BluetoothWixel",
    "date": 1458792784838,
    "dateString": "03/24/2016 04:13:04 a.m.",
    "sgv": 228,
    "direction": "Flat",
    "type": "sgv",
    "filtered": 232928,
    "unfiltered": 232928,
    "rssi": 100,
    "noise": 1,
    "glucose": 228
  },
  {
    "_id": "56f36826940a4faae1615c6c",
    "device": "xDrip-BluetoothWixel",
    "date": 1458792485329,
    "dateString": "03/24/2016 04:08:05 a.m.",
    "sgv": 228,
    "direction": "Flat",
    "type": "sgv",
    "filtered": 232448,
    "unfiltered": 232448,
    "rssi": 100,
    "noise": 1,
    "glucose": 228
  },
  {
    "_id": "56f366fb940a4faae1615c67",
    "device": "xDrip-BluetoothWixel",
    "date": 1458792184813,
    "dateString": "03/24/2016 04:03:04 a.m.",
    "sgv": 227,
    "direction": "Flat",
    "type": "sgv",
    "filtered": 231776,
    "unfiltered": 231776,
    "rssi": 100,
    "noise": 1,
    "glucose": 227
  },
  {
    "_id": "56f365cd940a4faae1615c61",
    "device": "xDrip-BluetoothWixel",
    "date": 1458791884788,
    "dateString": "03/24/2016 03:58:04 a.m.",
    "sgv": 226,
    "direction": "Flat",
    "type": "sgv",
    "filtered": 230464,
    "unfiltered": 230464,
    "rssi": 100,
    "noise": 1,
    "glucose": 226
  },
  {
    "_id": "56f364a1940a4faae1615c5b",
    "device": "xDrip-BluetoothWixel",
    "date": 1458791584618,
    "dateString": "03/24/2016 03:53:04 a.m.",
    "sgv": 224,
    "direction": "Flat",
    "type": "sgv",
    "filtered": 228640,
    "unfiltered": 228640,
    "rssi": 100,
    "noise": 1,
    "glucose": 224
  },
  {
    "_id": "56f36377940a4faae1615c53",
    "device": "xDrip-BluetoothWixel",
    "date": 1458791284823,
    "dateString": "03/24/2016 03:48:04 a.m.",
    "sgv": 222,
    "direction": "Flat",
    "type": "sgv",
    "filtered": 226784,
    "unfiltered": 226784,
    "rssi": 100,
    "noise": 1,
    "glucose": 222
  },
  {
    "_id": "56f36249940a4faae1615c4d",
    "device": "xDrip-BluetoothWixel",
    "date": 1458790984834,
    "dateString": "03/24/2016 03:43:04 a.m.",
    "sgv": 219,
    "direction": "Flat",
    "type": "sgv",
    "filtered": 224608,
    "unfiltered": 224608,
    "rssi": 100,
    "noise": 1,
    "glucose": 219
  },
  {
    "_id": "56f3611e940a4faae1615c47",
    "device": "xDrip-BluetoothWixel",
    "date": 1458790684682,
    "dateString": "03/24/2016 03:38:04 a.m.",
    "sgv": 220,
    "direction": "Flat",
    "type": "sgv",
    "filtered": 224992,
    "unfiltered": 224992,
    "rssi": 100,
    "noise": 1,
    "glucose": 220
  },
  {
    "_id": "56f35ff2940a4faae1615c40",
    "device": "xDrip-BluetoothWixel",
    "date": 1458790384806,
    "dateString": "03/24/2016 03:33:04 a.m.",
    "sgv": 221,
    "direction": "FortyFiveDown",
    "type": "sgv",
    "filtered": 226016,
    "unfiltered": 226016,
    "rssi": 100,
    "noise": 1,
    "glucose": 221
  },
  {
    "_id": "56f35ec6940a4faae1615c39",
    "device": "xDrip-BluetoothWixel",
    "date": 1458790084863,
    "dateString": "03/24/2016 03:28:04 a.m.",
    "sgv": 226,
    "direction": "Flat",
    "type": "sgv",
    "filtered": 231104,
    "unfiltered": 231104,
    "rssi": 100,
    "noise": 1,
    "glucose": 226
  }
]
