[
  {
    "_id": "56f71c2e940a4faae16178a6",
    "device": "xDrip-BluetoothWixel",
    "date": 1459035178120,
    "dateString": "03/26/2016 23:32:58 p.m.",
    "sgv": 201,
    "direction": "FortyFiveDown",
    "type": "sgv",
    "filtered": 200800,
    "unfiltered": 200800,
    "rssi": 100,
    "noise": 1,
    "glucose": 201
  },
  {
    "_id": "56f71b00940a4faae161789e",
    "device": "xDrip-BluetoothWixel",
    "date": 1459034878105,
    "dateString": "03/26/2016 23:27:58 p.m.",
    "sgv": 206,
    "direction": "FortyFiveDown",
    "type": "sgv",
    "filtered": 205216,
    "unfiltered": 205216,
    "rssi": 100,
    "noise": 1,
    "glucose": 206
  },
  {
    "_id": "56f719d4940a4faae1617894",
    "device": "xDrip-BluetoothWixel",
    "date": 1459034577099,
    "dateString": "03/26/2016 23:22:57 p.m.",
    "sgv": 213,
    "direction": "Flat",
    "type": "sgv",
    "filtered": 210752,
    "unfiltered": 210752,
    "rssi": 100,
    "noise": 1,
    "glucose": 213
  },
  {
    "_id": "56f718a9940a4faae1617889",
    "device": "xDrip-BluetoothWixel",
    "date": 1459034277323,
    "dateString": "03/26/2016 23:17:57 p.m.",
    "sgv": 218,
    "direction": "Flat",
    "type": "sgv",
    "filtered": 214400,
    "unfiltered": 214400,
    "rssi": 100,
    "noise": 1,
    "glucose": 218
  },
  {
    "_id": "56f7177d940a4faae1617880",
    "device": "xDrip-BluetoothWixel",
    "date": 1459033977341,
    "dateString": "03/26/2016 23:12:57 p.m.",
    "sgv": 221,
    "direction": "Flat",
    "type": "sgv",
    "filtered": 217312,
    "unfiltered": 217312,
    "rssi": 100,
    "noise": 1,
    "glucose": 221
  },
  {
    "_id": "56f71657940a4faae1617873",
    "device": "xDrip-BluetoothWixel",
    "date": 1459033677329,
    "dateString": "03/26/2016 23:07:57 p.m.",
    "sgv": 221,
    "direction": "Flat",
    "type": "sgv",
    "filtered": 217600,
    "unfiltered": 217600,
    "rssi": 100,
    "noise": 1,
    "glucose": 221
  },
  {
    "_id": "56f71652940a4faae1617872",
    "device": "xDrip-BluetoothWixel",
    "type": "cal",
    "date": 1459033554829,
    "dateString": "03/26/2016 23:05:54 p.m.",
    "slope": 1219,
    "intercept": 35,
    "scale": 1
  },
  {
    "_id": "56f715d7940a4faae161786e",
    "device": "xDrip-BluetoothWixel",
    "type": "cal",
    "date": 1459033554829,
    "dateString": "03/26/2016 23:05:54 p.m.",
    "slope": 0,
    "intercept": 0,
    "scale": 1
  },
  {
    "_id": "56f715d6940a4faae161786d",
    "device": "xDrip-BluetoothWixel",
    "type": "mbg",
    "date": 1459033554829,
    "dateString": "03/26/2016 23:05:54 p.m.",
    "mbg": 225.2275
  },
  {
    "_id": "56f71524940a4faae1617866",
    "device": "xDrip-BluetoothWixel",
    "date": 1459033377309,
    "dateString": "03/26/2016 23:02:57 p.m.",
    "sgv": 222,
    "direction": "Flat",
    "type": "sgv",
    "filtered": 217376,
    "unfiltered": 217376,
    "rssi": 100,
    "noise": 1,
    "glucose": 222
  }
]
